Workbook

Sheet CorST
A1: Слово | B1: Частота-CorST | C1: IPM-CorST | D1: Ранг-CorST | E1: Номер строки в RLC | F1: IPM-RLC
A2: в | B2: 35889 | C2: 11520.564 | D2: 1 | E2: =MATCH(A2,RLC!$A$2:$A$10993,0) -> 2 | F2: {=IFERROR(INDEX(RLC!$C$2:$C$10993,E2),"")} -> 37993.234
A3: и | B3: 31435 | C3: 10090.806 | D3: =IF(C3=C2,D2,D2+1) -> 2 | E3: =MATCH(A3,RLC!$A$2:$A$10993,0) -> 1 | F3: {=IFERROR(INDEX(RLC!$C$2:$C$10993,E3),"")} -> 38334.702
A4: на | B4: 13212 | C4: 4241.1239 | D4: =IF(C4=C3,D3,D3+1) -> 3 | E4: =MATCH(A4,RLC!$A$2:$A$10993,0) -> 4 | F4: {=IFERROR(INDEX(RLC!$C$2:$C$10993,E4),"")} -> 13265.412
A5: не | B5: 11811 | C5: 3791.3953 | D5: =IF(C5=C4,D4,D4+1) -> 4 | E5: =MATCH(A5,RLC!$A$2:$A$10993,0) -> 5 | F5: {=IFERROR(INDEX(RLC!$C$2:$C$10993,E5),"")} -> 12860.168
A6: с | B6: 11363 | C6: 3647.5848 | D6: =IF(C6=C5,D5,D5+1) -> 5 | E6: =MATCH(A6,RLC!$A$2:$A$10993,0) -> 7 | F6: {=IFERROR(INDEX(RLC!$C$2:$C$10993,E6),"")} -> 9178.432
A7: что | B7: 10265 | C7: 3295.1208 | D7: =IF(C7=C6,D6,D6+1) -> 6 | E7: =MATCH(A7,RLC!$A$2:$A$10993,0) -> 3 | F7: {=IFERROR(INDEX(RLC!$C$2:$C$10993,E7),"")} -> 16305.402
A8: как | B8: 7396 | C8: 2374.1562 | D8: =IF(C8=C7,D7,D7+1) -> 7 | E8: =MATCH(A8,RLC!$A$2:$A$10993,0) -> 8 | F8: {=IFERROR(INDEX(RLC!$C$2:$C$10993,E8),"")} -> 8273.6097
A9: к | B9: 6790 | C9: 2179.6269 | D9: =IF(C9=C8,D8,D8+1) -> 8 | E9: =MATCH(A9,RLC!$A$2:$A$10993,0) -> 14 | F9: {=IFERROR(INDEX(RLC!$C$2:$C$10993,E9),"")} -> 4742.0127
A10: а | B10: 5924 | C10: 1901.6362 | D10: =IF(C10=C9,D9,D9+1) -> 9 | E10: =MATCH(A10,RLC!$A$2:$A$10993,0) -> 19 | F10: {=IFERROR(INDEX(RLC!$C$2:$C$10993,E10),"")} -> 3449.2197
A11: для | B11: 5652 | C11: 1814.3227 | D11: =IF(C11=C10,D10,D10+1) -> 10 | E11: =MATCH(A11,RLC!$A$2:$A$10993,0) -> 13 | F11: {=IFERROR(INDEX(RLC!$C$2:$C$10993,E11),"")} -> 5009.0748
A12: по | B12: 5634 | C12: 1808.5447 | D12: =IF(C12=C11,D11,D11+1) -> 11 | E12: =MATCH(A12,RLC!$A$2:$A$10993,0) -> 15 | F12: {=IFERROR(INDEX(RLC!$C$2:$C$10993,E12),"")} -> 4641.034
A13: о | B13: 4912 | C13: 1576.7787 | D13: =IF(C13=C12,D12,D12+1) -> 12 | E13: =MATCH(A13,RLC!$A$2:$A$10993,0) -> 12 | F13: {=IFERROR(INDEX(RLC!$C$2:$C$10993,E13),"")} -> 5022.3615
A14: из | B14: 4365 | C14: 1401.1887 | D14: =IF(C14=C13,D13,D13+1) -> 13 | E14: =MATCH(A14,RLC!$A$2:$A$10993,0) -> 16 | F14: {=IFERROR(INDEX(RLC!$C$2:$C$10993,E14),"")} -> 4432.4333
... A1349: форм | B1349: 92 | C1349: 29.532501 | D1349: =IF(C1349=C1348,D1348,D1348+1) -> 464 | E1349: =MATCH(A1349,RLC!$A$2:$A$10993,0) -> 5288 | F1349: {=IFERROR(INDEX(RLC!$C$2:$C$10993,E1349),"")} -> 21.258673
A1350: школе | B1350: 92 | C1350: 29.532501 | D1350: =IF(C1350=C1349,D1349,D1349+1) -> 464 | E1350: =MATCH(A1350,RLC!$A$2:$A$10993,0) -> 403 | F1350: {=IFERROR(INDEX(RLC!$C$2:$C$10993,E1350),"")} -> 259.09008 | G1350: =C1350>E1350 -> FALSE
A1351: элементов | B1351: 92 | C1351: 29.532501 | D1351: =IF(C1351=C1350,D1350,D1350+1) -> 464 | E1351: =MATCH(A1351,RLC!$A$2:$A$10993,0) -> 4111 | F1351: {=IFERROR(INDEX(RLC!$C$2:$C$10993,E1351),"")} -> 27.902008
A1352: этими | B1352: 92 | C1352: 29.532501 | D1352: =IF(C1352=C1351,D1351,D1351+1) -> 464 | E1352: =MATCH(A1352,RLC!$A$2:$A$10993,0) -> 1491 | F1352: {=IFERROR(INDEX(RLC!$C$2:$C$10993,E1352),"")} -> 77.062689
A1353: артикля | B1353: 91 | C1353: 29.211495 | D1353: =IF(C1353=C1352,D1352,D1352+1) -> 465 | E1353: =MATCH(A1353,RLC!$A$2:$A$10993,0) -> #N/A | F1353: {=IFERROR(INDEX(RLC!$C$2:$C$10993,E1353),"")}
A1354: всему | B1354: 91 | C1354: 29.211495 | D1354: =IF(C1354=C1353,D1353,D1353+1) -> 465 | E1354: =MATCH(A1354,RLC!$A$2:$A$10993,0) -> 740 | F1354: {=IFERROR(INDEX(RLC!$C$2:$C$10993,E1354),"")} -> 144.82471
A1355: выполнения | B1355: 91 | C1355: 29.211495 | D1355: =IF(C1355=C1354,D1354,D1354+1) -> 465 | E1355: =MATCH(A1355,RLC!$A$2:$A$10993,0) -> #N/A | F1355: {=IFERROR(INDEX(RLC!$C$2:$C$10993,E1355),"")}
A1356: достоевский | B1356: 91 | C1356: 29.211495 | D1356: =IF(C1356=C1355,D1355,D1355+1) -> 465 | E1356: =MATCH(A1356,RLC!$A$2:$A$10993,0) -> #N/A | F1356: {=IFERROR(INDEX(RLC!$C$2:$C$10993,E1356),"")}
A1357: менеджмента | B1357: 91 | C1357: 29.211495 | D1357: =IF(C1357=C1356,D1356,D1356+1) -> 465 | E1357: =MATCH(A1357,RLC!$A$2:$A$10993,0) -> 2857 | F1357: {=IFERROR(INDEX(RLC!$C$2:$C$10993,E1357),"")} -> 39.860012
A1358: наша | B1358: 91 | C1358: 29.211495 | D1358: =IF(C1358=C1357,D1357,D1357+1) -> 465 | E1358: =MATCH(A1358,RLC!$A$2:$A$10993,0) -> 550 | F1358: {=IFERROR(INDEX(RLC!$C$2:$C$10993,E1358),"")} -> 193.98539
A1359: поднятая | B1359: 91 | C1359: 29.211495 | D1359: =IF(C1359=C1358,D1358,D1358+1) -> 465 | E1359: =MATCH(A1359,RLC!$A$2:$A$10993,0) -> #N/A | F1359: {=IFERROR(INDEX(RLC!$C$2:$C$10993,E1359),"")}
A1360: постепенно | B1360: 91 | C1360: 29.211495 | D1360: =IF(C1360=C1359,D1359,D1359+1) -> 465 | E1360: =MATCH(A1360,RLC!$A$2:$A$10993,0) -> 2468 | F1360: {=IFERROR(INDEX(RLC!$C$2:$C$10993,E1360),"")} -> 46.503347
A1361: рублей | B1361: 91 | C1361: 29.211495 | D1361: =IF(C1361=C1360,D1360,D1360+1) -> 465 | E1361: =MATCH(A1361,RLC!$A$2:$A$10993,0) -> 1696 | F1361: {=IFERROR(INDEX(RLC!$C$2:$C$10993,E1361),"")} -> 67.76202
A1362: сегодняшний | B1362: 91 | C1362: 29.211495 | D1362: =IF(C1362=C1361,D1361,D1361+1) -> 465 | E1362: =MATCH(A1362,RLC!$A$2:$A$10993,0) -> 1872 | F1362: {=IFERROR(INDEX(RLC!$C$2:$C$10993,E1362),"")} -> 62.447352
... A1716: чехов | B1716: 73 | C1716: 23.433397 | D1716: =IF(C1716=C1715,D1715,D1715+1) -> 483 | E1716: =MATCH(A1716,RLC!$A$2:$A$10993,0) -> #N/A | F1716: {=IFERROR(INDEX(RLC!$C$2:$C$10993,E1716),"")}
A1717: шапочка | B1717: 73 | C1717: 23.433397 | D1717: =IF(C1717=C1716,D1716,D1716+1) -> 483 | E1717: =MATCH(A1717,RLC!$A$2:$A$10993,0) -> 3339 | F1717: {=IFERROR(INDEX(RLC!$C$2:$C$10993,E1717),"")} -> 34.545343 | G1717: =C1717>E1717 -> FALSE
A1718: широко | B1718: 73 | C1718: 23.433397 | D1718: =IF(C1718=C1717,D1717,D1717+1) -> 483 | E1718: =MATCH(A1718,RLC!$A$2:$A$10993,0) -> 1584 | F1718: {=IFERROR(INDEX(RLC!$C$2:$C$10993,E1718),"")} -> 73.076688 | G1718: =C1718>E1718 -> FALSE
A1719: эмоций | B1719: 73 | C1719: 23.433397 | D1719: =IF(C1719=C1718,D1718,D1718+1) -> 483 | E1719: =MATCH(A1719,RLC!$A$2:$A$10993,0) -> 6912 | F1719: {=IFERROR(INDEX(RLC!$C$2:$C$10993,E1719),"")} -> 15.944005
A1720: большие | B1720: 72 | C1720: 23.112392 | D1720: =IF(C1720=C1719,D1719,D1719+1) -> 484 | E1720: =MATCH(A1720,RLC!$A$2:$A$10993,0) -> 836 | F1720: {=IFERROR(INDEX(RLC!$C$2:$C$10993,E1720),"")} -> 128.8807
A1721: большого | B1721: 72 | C1721: 23.112392 | D1721: =IF(C1721=C1720,D1720,D1720+1) -> 484 | E1721: =MATCH(A1721,RLC!$A$2:$A$10993,0) -> 2650 | F1721: {=IFERROR(INDEX(RLC!$C$2:$C$10993,E1721),"")} -> 42.517346
A1722: ведет | B1722: 72 | C1722: 23.112392 | D1722: =IF(C1722=C1721,D1721,D1721+1) -> 484 | E1722: =MATCH(A1722,RLC!$A$2:$A$10993,0) -> 3482 | F1722: {=IFERROR(INDEX(RLC!$C$2:$C$10993,E1722),"")} -> 31.888009
A1723: вниз | B1723: 72 | C1723: 23.112392 | D1723: =IF(C1723=C1722,D1722,D1722+1) -> 484 | E1723: =MATCH(A1723,RLC!$A$2:$A$10993,0) -> 2831 | F1723: {=IFERROR(INDEX(RLC!$C$2:$C$10993,E1723),"")} -> 39.860012
A1724: вузов | B1724: 72 | C1724: 23.112392 | D1724: =IF(C1724=C1723,D1723,D1723+1) -> 484 | E1724: =MATCH(A1724,RLC!$A$2:$A$10993,0) -> 6051 | F1724: {=IFERROR(INDEX(RLC!$C$2:$C$10993,E1724),"")} -> 17.272672
A1725: выражений | B1725: 72 | C1725: 23.112392 | D1725: =IF(C1725=C1724,D1724,D1724+1) -> 484 | E1725: =MATCH(A1725,RLC!$A$2:$A$10993,0) -> 3785 | F1725: {=IFERROR(INDEX(RLC!$C$2:$C$10993,E1725),"")} -> 29.230675
A1726: гражданским | B1726: 72 | C1726: 23.112392 | D1726: =IF(C1726=C1725,D1725,D1725+1) -> 484 | E1726: =MATCH(A1726,RLC!$A$2:$A$10993,0) -> #N/A | F1726: {=IFERROR(INDEX(RLC!$C$2:$C$10993,E1726),"")}
A1727: изучить | B1727: 72 | C1727: 23.112392 | D1727: =IF(C1727=C1726,D1726,D1726+1) -> 484 | E1727: =MATCH(A1727,RLC!$A$2:$A$10993,0) -> 4371 | F1727: {=IFERROR(INDEX(RLC!$C$2:$C$10993,E1727),"")} -> 25.244674
A1728: ин | B1728: 72 | C1728: 23.112392 | D1728: =IF(C1728=C1727,D1727,D1727+1) -> 484 | E1728: =MATCH(A1728,RLC!$A$2:$A$10993,0) -> #N/A | F1728: {=IFERROR(INDEX(RLC!$C$2:$C$10993,E1728),"")}
A1729: интернета | B1729: 72 | C1729: 23.112392 | D1729: =IF(C1729=C1728,D1728,D1728+1) -> 484 | E1729: =MATCH(A1729,RLC!$A$2:$A$10993,0) -> 2959 | F1729: {=IFERROR(INDEX(RLC!$C$2:$C$10993,E1729),"")} -> 38.531345
A1730: когнитивных | B1730: 72 | C1730: 23.112392 | D1730: =IF(C1730=C1729,D1729,D1729+1) -> 484 | E1730: =MATCH(A1730,RLC!$A$2:$A$10993,0) -> #N/A | F1730: {=IFERROR(INDEX(RLC!$C$2:$C$10993,E1730),"")}
... A2090: чтение | B2090: 61 | C2090: 19.581332 | D2090: =IF(C2090=C2089,D2089,D2089+1) -> 495 | E2090: =MATCH(A2090,RLC!$A$2:$A$10993,0) -> 2646 | F2090: {=IFERROR(INDEX(RLC!$C$2:$C$10993,E2090),"")} -> 43.846013
A2091: школы | B2091: 61 | C2091: 19.581332 | D2091: =IF(C2091=C2090,D2090,D2090+1) -> 495 | E2091: =MATCH(A2091,RLC!$A$2:$A$10993,0) -> 541 | F2091: {=IFERROR(INDEX(RLC!$C$2:$C$10993,E2091),"")} -> 197.97139 | G2091: =C2091>E2091 -> FALSE
A2092: больших | B2092: 60 | C2092: 19.260326 | D2092: =IF(C2092=C2091,D2091,D2091+1) -> 496 | E2092: =MATCH(A2092,RLC!$A$2:$A$10993,0) -> 1081 | F2092: {=IFERROR(INDEX(RLC!$C$2:$C$10993,E2092),"")} -> 102.30736
A2093: будем | B2093: 60 | C2093: 19.260326 | D2093: =IF(C2093=C2092,D2092,D2092+1) -> 496 | E2093: =MATCH(A2093,RLC!$A$2:$A$10993,0) -> 1096 | F2093: {=IFERROR(INDEX(RLC!$C$2:$C$10993,E2093),"")} -> 100.9787
A2094: вариативность | B2094: 60 | C2094: 19.260326 | D2094: =IF(C2094=C2093,D2093,D2093+1) -> 496 | E2094: =MATCH(A2094,RLC!$A$2:$A$10993,0) -> #N/A | F2094: {=IFERROR(INDEX(RLC!$C$2:$C$10993,E2094),"")}
A2095: возмещения | B2095: 60 | C2095: 19.260326 | D2095: =IF(C2095=C2094,D2094,D2094+1) -> 496 | E2095: =MATCH(A2095,RLC!$A$2:$A$10993,0) -> #N/A | F2095: {=IFERROR(INDEX(RLC!$C$2:$C$10993,E2095),"")}
A2096: возможностей | B2096: 60 | C2096: 19.260326 | D2096: =IF(C2096=C2095,D2095,D2095+1) -> 496 | E2096: =MATCH(A2096,RLC!$A$2:$A$10993,0) -> 2834 | F2096: {=IFERROR(INDEX(RLC!$C$2:$C$10993,E2096),"")} -> 39.860012
A2097: выяснить | B2097: 60 | C2097: 19.260326 | D2097: =IF(C2097=C2096,D2096,D2096+1) -> 496 | E2097: =MATCH(A2097,RLC!$A$2:$A$10993,0) -> 7546 | F2097: {=IFERROR(INDEX(RLC!$C$2:$C$10993,E2097),"")} -> 13.286671
A2098: гипотез | B2098: 60 | C2098: 19.260326 | D2098: =IF(C2098=C2097,D2097,D2097+1) -> 496 | E2098: =MATCH(A2098,RLC!$A$2:$A$10993,0) -> #N/A | F2098: {=IFERROR(INDEX(RLC!$C$2:$C$10993,E2098),"")}
A2099: голове | B2099: 60 | C2099: 19.260326 | D2099: =IF(C2099=C2098,D2098,D2098+1) -> 496 | E2099: =MATCH(A2099,RLC!$A$2:$A$10993,0) -> 2130 | F2099: {=IFERROR(INDEX(RLC!$C$2:$C$10993,E2099),"")} -> 53.146682
A2100: гражданском | B2100: 60 | C2100: 19.260326 | D2100: =IF(C2100=C2099,D2099,D2099+1) -> 496 | E2100: =MATCH(A2100,RLC!$A$2:$A$10993,0) -> #N/A | F2100: {=IFERROR(INDEX(RLC!$C$2:$C$10993,E2100),"")}
A2101: дается | B2101: 60 | C2101: 19.260326 | D2101: =IF(C2101=C2100,D2100,D2100+1) -> 496 | E2101: =MATCH(A2101,RLC!$A$2:$A$10993,0) -> 4144 | F2101: {=IFERROR(INDEX(RLC!$C$2:$C$10993,E2101),"")} -> 26.573341
A2102: дальнейшего | B2102: 60 | C2102: 19.260326 | D2102: =IF(C2102=C2101,D2101,D2101+1) -> 496 | E2102: =MATCH(A2102,RLC!$A$2:$A$10993,0) -> #N/A | F2102: {=IFERROR(INDEX(RLC!$C$2:$C$10993,E2102),"")}
A2103: другая | B2103: 60 | C2103: 19.260326 | D2103: =IF(C2103=C2102,D2102,D2102+1) -> 496 | E2103: =MATCH(A2103,RLC!$A$2:$A$10993,0) -> 1156 | F2103: {=IFERROR(INDEX(RLC!$C$2:$C$10993,E2103),"")} -> 96.992695
... A2510: фоне | B2510: 50 | C2510: 16.050272 | D2510: =IF(C2510=C2509,D2509,D2509+1) -> 506 | E2510: =MATCH(A2510,RLC!$A$2:$A$10993,0) -> #N/A | F2510: {=IFERROR(INDEX(RLC!$C$2:$C$10993,E2510),"")}
A2511: широкий | B2511: 50 | C2511: 16.050272 | D2511: =IF(C2511=C2510,D2510,D2510+1) -> 506 | E2511: =MATCH(A2511,RLC!$A$2:$A$10993,0) -> 6906 | F2511: {=IFERROR(INDEX(RLC!$C$2:$C$10993,E2511),"")} -> 15.944005 | G2511: =C2511>E2511 -> FALSE
A2512: адресован | B2512: 49 | C2512: 15.729267 | D2512: =IF(C2512=C2511,D2511,D2511+1) -> 507 | E2512: =MATCH(A2512,RLC!$A$2:$A$10993,0) -> #N/A | F2512: {=IFERROR(INDEX(RLC!$C$2:$C$10993,E2512),"")}
A2513: база | B2513: 49 | C2513: 15.729267 | D2513: =IF(C2513=C2512,D2512,D2512+1) -> 507 | E2513: =MATCH(A2513,RLC!$A$2:$A$10993,0) -> #N/A | F2513: {=IFERROR(INDEX(RLC!$C$2:$C$10993,E2513),"")}
A2514: вариативности | B2514: 49 | C2514: 15.729267 | D2514: =IF(C2514=C2513,D2513,D2513+1) -> 507 | E2514: =MATCH(A2514,RLC!$A$2:$A$10993,0) -> #N/A | F2514: {=IFERROR(INDEX(RLC!$C$2:$C$10993,E2514),"")}
A2515: введения | B2515: 49 | C2515: 15.729267 | D2515: =IF(C2515=C2514,D2514,D2514+1) -> 507 | E2515: =MATCH(A2515,RLC!$A$2:$A$10993,0) -> 7508 | F2515: {=IFERROR(INDEX(RLC!$C$2:$C$10993,E2515),"")} -> 13.286671
A2516: видел | B2516: 49 | C2516: 15.729267 | D2516: =IF(C2516=C2515,D2515,D2515+1) -> 507 | E2516: =MATCH(A2516,RLC!$A$2:$A$10993,0) -> 1925 | F2516: {=IFERROR(INDEX(RLC!$C$2:$C$10993,E2516),"")} -> 59.790017
A2517: высокий | B2517: 49 | C2517: 15.729267 | D2517: =IF(C2517=C2516,D2516,D2516+1) -> 507 | E2517: =MATCH(A2517,RLC!$A$2:$A$10993,0) -> 2128 | F2517: {=IFERROR(INDEX(RLC!$C$2:$C$10993,E2517),"")} -> 53.146682
A2518: выходит | B2518: 49 | C2518: 15.729267 | D2518: =IF(C2518=C2517,D2517,D2517+1) -> 507 | E2518: =MATCH(A2518,RLC!$A$2:$A$10993,0) -> 3636 | F2518: {=IFERROR(INDEX(RLC!$C$2:$C$10993,E2518),"")} -> 30.559342
A2519: герои | B2519: 49 | C2519: 15.729267 | D2519: =IF(C2519=C2518,D2518,D2518+1) -> 507 | E2519: =MATCH(A2519,RLC!$A$2:$A$10993,0) -> 2501 | F2519: {=IFERROR(INDEX(RLC!$C$2:$C$10993,E2519),"")} -> 45.17468
A2520: глагольных | B2520: 49 | C2520: 15.729267 | D2520: =IF(C2520=C2519,D2519,D2519+1) -> 507 | E2520: =MATCH(A2520,RLC!$A$2:$A$10993,0) -> #N/A | F2520: {=IFERROR(INDEX(RLC!$C$2:$C$10993,E2520),"")}
A2521: гпк | B2521: 49 | C2521: 15.729267 | D2521: =IF(C2521=C2520,D2520,D2520+1) -> 507 | E2521: =MATCH(A2521,RLC!$A$2:$A$10993,0) -> #N/A | F2521: {=IFERROR(INDEX(RLC!$C$2:$C$10993,E2521),"")}
A2522: егэ | B2522: 49 | C2522: 15.729267 | D2522: =IF(C2522=C2521,D2521,D2521+1) -> 507 | E2522: =MATCH(A2522,RLC!$A$2:$A$10993,0) -> 3048 | F2522: {=IFERROR(INDEX(RLC!$C$2:$C$10993,E2522),"")} -> 37.202678
A2523: единственный | B2523: 49 | C2523: 15.729267 | D2523: =IF(C2523=C2522,D2522,D2522+1) -> 507 | E2523: =MATCH(A2523,RLC!$A$2:$A$10993,0) -> 1891 | F2523: {=IFERROR(INDEX(RLC!$C$2:$C$10993,E2523),"")} -> 61.118685
... A2664: человеке | B2664: 47 | C2664: 15.087256 | D2664: =IF(C2664=C2663,D2663,D2663+1) -> 509 | E2664: =MATCH(A2664,RLC!$A$2:$A$10993,0) -> 2555 | F2664: {=IFERROR(INDEX(RLC!$C$2:$C$10993,E2664),"")} -> 45.17468
A2665: шаг | B2665: 47 | C2665: 15.087256 | D2665: =IF(C2665=C2664,D2664,D2664+1) -> 509 | E2665: =MATCH(A2665,RLC!$A$2:$A$10993,0) -> 2737 | F2665: {=IFERROR(INDEX(RLC!$C$2:$C$10993,E2665),"")} -> 42.517346 | G2665: =C2665>E2665 -> FALSE
A2666: авторских | B2666: 46 | C2666: 14.76625 | D2666: =IF(C2666=C2665,D2665,D2665+1) -> 510 | E2666: =MATCH(A2666,RLC!$A$2:$A$10993,0) -> #N/A | F2666: {=IFERROR(INDEX(RLC!$C$2:$C$10993,E2666),"")}
A2667: будь | B2667: 46 | C2667: 14.76625 | D2667: =IF(C2667=C2666,D2666,D2666+1) -> 510 | E2667: =MATCH(A2667,RLC!$A$2:$A$10993,0) -> 3244 | F2667: {=IFERROR(INDEX(RLC!$C$2:$C$10993,E2667),"")} -> 34.545343
A2668: бытия | B2668: 46 | C2668: 14.76625 | D2668: =IF(C2668=C2667,D2667,D2667+1) -> 510 | E2668: =MATCH(A2668,RLC!$A$2:$A$10993,0) -> #N/A | F2668: {=IFERROR(INDEX(RLC!$C$2:$C$10993,E2668),"")}
A2669: вводит | B2669: 46 | C2669: 14.76625 | D2669: =IF(C2669=C2668,D2668,D2668+1) -> 510 | E2669: =MATCH(A2669,RLC!$A$2:$A$10993,0) -> #N/A | F2669: {=IFERROR(INDEX(RLC!$C$2:$C$10993,E2669),"")}
A2670: вещь | B2670: 46 | C2670: 14.76625 | D2670: =IF(C2670=C2669,D2669,D2669+1) -> 510 | E2670: =MATCH(A2670,RLC!$A$2:$A$10993,0) -> 2654 | F2670: {=IFERROR(INDEX(RLC!$C$2:$C$10993,E2670),"")} -> 42.517346
A2671: взаимодействии | B2671: 46 | C2671: 14.76625 | D2671: =IF(C2671=C2670,D2670,D2670+1) -> 510 | E2671: =MATCH(A2671,RLC!$A$2:$A$10993,0) -> #N/A | F2671: {=IFERROR(INDEX(RLC!$C$2:$C$10993,E2671),"")}
A2672: выборки | B2672: 46 | C2672: 14.76625 | D2672: =IF(C2672=C2671,D2671,D2671+1) -> 510 | E2672: =MATCH(A2672,RLC!$A$2:$A$10993,0) -> #N/A | F2672: {=IFERROR(INDEX(RLC!$C$2:$C$10993,E2672),"")}
A2673: выделены | B2673: 46 | C2673: 14.76625 | D2673: =IF(C2673=C2672,D2672,D2672+1) -> 510 | E2673: =MATCH(A2673,RLC!$A$2:$A$10993,0) -> #N/A | F2673: {=IFERROR(INDEX(RLC!$C$2:$C$10993,E2673),"")}
A2674: гипотезу | B2674: 46 | C2674: 14.76625 | D2674: =IF(C2674=C2673,D2673,D2673+1) -> 510 | E2674: =MATCH(A2674,RLC!$A$2:$A$10993,0) -> #N/A | F2674: {=IFERROR(INDEX(RLC!$C$2:$C$10993,E2674),"")}
A2675: государств | B2675: 46 | C2675: 14.76625 | D2675: =IF(C2675=C2674,D2674,D2674+1) -> 510 | E2675: =MATCH(A2675,RLC!$A$2:$A$10993,0) -> 990 | F2675: {=IFERROR(INDEX(RLC!$C$2:$C$10993,E2675),"")} -> 111.60803
A2676: доме | B2676: 46 | C2676: 14.76625 | D2676: =IF(C2676=C2675,D2675,D2675+1) -> 510 | E2676: =MATCH(A2676,RLC!$A$2:$A$10993,0) -> 906 | F2676: {=IFERROR(INDEX(RLC!$C$2:$C$10993,E2676),"")} -> 120.9087
A2677: думать | B2677: 46 | C2677: 14.76625 | D2677: =IF(C2677=C2676,D2676,D2676+1) -> 510 | E2677: =MATCH(A2677,RLC!$A$2:$A$10993,0) -> 719 | F2677: {=IFERROR(INDEX(RLC!$C$2:$C$10993,E2677),"")} -> 147.48204
... A2830: ценностей | B2830: 44 | C2830: 14.124239 | D2830: =IF(C2830=C2829,D2829,D2829+1) -> 512 | E2830: =MATCH(A2830,RLC!$A$2:$A$10993,0) -> 1924 | F2830: {=IFERROR(INDEX(RLC!$C$2:$C$10993,E2830),"")} -> 61.118685
A2831: широкого | B2831: 44 | C2831: 14.124239 | D2831: =IF(C2831=C2830,D2830,D2830+1) -> 512 | E2831: =MATCH(A2831,RLC!$A$2:$A$10993,0) -> 5301 | F2831: {=IFERROR(INDEX(RLC!$C$2:$C$10993,E2831),"")} -> 21.258673 | G2831: =C2831>E2831 -> FALSE
A2832: широкой | B2832: 44 | C2832: 14.124239 | D2832: =IF(C2832=C2831,D2831,D2831+1) -> 512 | E2832: =MATCH(A2832,RLC!$A$2:$A$10993,0) -> 1997 | F2832: {=IFERROR(INDEX(RLC!$C$2:$C$10993,E2832),"")} -> 58.46135 | G2832: =C2832>E2832 -> FALSE
A2833: экономиста | B2833: 44 | C2833: 14.124239 | D2833: =IF(C2833=C2832,D2832,D2832+1) -> 512 | E2833: =MATCH(A2833,RLC!$A$2:$A$10993,0) -> #N/A | F2833: {=IFERROR(INDEX(RLC!$C$2:$C$10993,E2833),"")}
A2834: экономического | B2834: 44 | C2834: 14.124239 | D2834: =IF(C2834=C2833,D2833,D2833+1) -> 512 | E2834: =MATCH(A2834,RLC!$A$2:$A$10993,0) -> 916 | F2834: {=IFERROR(INDEX(RLC!$C$2:$C$10993,E2834),"")} -> 120.9087
A2835: эксперта | B2835: 44 | C2835: 14.124239 | D2835: =IF(C2835=C2834,D2834,D2834+1) -> 512 | E2835: =MATCH(A2835,RLC!$A$2:$A$10993,0) -> #N/A | F2835: {=IFERROR(INDEX(RLC!$C$2:$C$10993,E2835),"")}
A2836: января | B2836: 44 | C2836: 14.124239 | D2836: =IF(C2836=C2835,D2835,D2835+1) -> 512 | E2836: =MATCH(A2836,RLC!$A$2:$A$10993,0) -> 1412 | F2836: {=IFERROR(INDEX(RLC!$C$2:$C$10993,E2836),"")} -> 81.04869
A2837: абстрактное | B2837: 43 | C2837: 13.803234 | D2837: =IF(C2837=C2836,D2836,D2836+1) -> 513 | E2837: =MATCH(A2837,RLC!$A$2:$A$10993,0) -> #N/A | F2837: {=IFERROR(INDEX(RLC!$C$2:$C$10993,E2837),"")}
A2838: автору | B2838: 43 | C2838: 13.803234 | D2838: =IF(C2838=C2837,D2837,D2837+1) -> 513 | E2838: =MATCH(A2838,RLC!$A$2:$A$10993,0) -> 6003 | F2838: {=IFERROR(INDEX(RLC!$C$2:$C$10993,E2838),"")} -> 17.272672
A2839: включая | B2839: 43 | C2839: 13.803234 | D2839: =IF(C2839=C2838,D2838,D2838+1) -> 513 | E2839: =MATCH(A2839,RLC!$A$2:$A$10993,0) -> 1414 | F2839: {=IFERROR(INDEX(RLC!$C$2:$C$10993,E2839),"")} -> 79.720023
A2840: встретить | B2840: 43 | C2840: 13.803234 | D2840: =IF(C2840=C2839,D2839,D2839+1) -> 513 | E2840: =MATCH(A2840,RLC!$A$2:$A$10993,0) -> 4554 | F2840: {=IFERROR(INDEX(RLC!$C$2:$C$10993,E2840),"")} -> 23.916007
A2841: выяснилось | B2841: 43 | C2841: 13.803234 | D2841: =IF(C2841=C2840,D2840,D2840+1) -> 513 | E2841: =MATCH(A2841,RLC!$A$2:$A$10993,0) -> 6484 | F2841: {=IFERROR(INDEX(RLC!$C$2:$C$10993,E2841),"")} -> 15.944005
A2842: грамматика | B2842: 43 | C2842: 13.803234 | D2842: =IF(C2842=C2841,D2841,D2841+1) -> 513 | E2842: =MATCH(A2842,RLC!$A$2:$A$10993,0) -> 6064 | F2842: {=IFERROR(INDEX(RLC!$C$2:$C$10993,E2842),"")} -> 17.272672
A2843: движений | B2843: 43 | C2843: 13.803234 | D2843: =IF(C2843=C2842,D2842,D2842+1) -> 513 | E2843: =MATCH(A2843,RLC!$A$2:$A$10993,0) -> 4346 | F2843: {=IFERROR(INDEX(RLC!$C$2:$C$10993,E2843),"")} -> 25.244674
A2844: доказывает | B2844: 43 | C2844: 13.803234 | D2844: =IF(C2844=C2843,D2843,D2843+1) -> 513 | E2844: =MATCH(A2844,RLC!$A$2:$A$10993,0) -> 2363 | F2844: {=IFERROR(INDEX(RLC!$C$2:$C$10993,E2844),"")} -> 47.832014
...

Sheet RLC
A1: Слово | B1: Частота-RLC | C1: IPM-RLC | D1: Ранг-RLC | E1: Номер строки в CorST
A2: и | B2: 28852 | C2: 38334.702 | D2: 1 | E2: =MATCH(A2,CorST!$A$2:$A$8126,0) -> 2
A3: в | B3: 28595 | C3: 37993.234 | D3: =IF(C3=C2,D2,D2+1) -> 2 | E3: =MATCH(A3,CorST!$A$2:$A$8126,0) -> 1
A4: что | B4: 12272 | C4: 16305.402 | D4: =IF(C4=C3,D3,D3+1) -> 3 | E4: =MATCH(A4,CorST!$A$2:$A$8126,0) -> 6
A5: на | B5: 9984 | C5: 13265.412 | D5: =IF(C5=C4,D4,D4+1) -> 4 | E5: =MATCH(A5,CorST!$A$2:$A$8126,0) -> 3
A6: не | B6: 9679 | C6: 12860.168 | D6: =IF(C6=C5,D5,D5+1) -> 5 | E6: =MATCH(A6,CorST!$A$2:$A$8126,0) -> 4
A7: я | B7: 8489 | C7: 11279.055 | D7: =IF(C7=C6,D6,D6+1) -> 6 | E7: =MATCH(A7,CorST!$A$2:$A$8126,0) -> 23
A8: с | B8: 6908 | C8: 9178.432 | D8: =IF(C8=C7,D7,D7+1) -> 7 | E8: =MATCH(A8,CorST!$A$2:$A$8126,0) -> 5
A9: как | B9: 6227 | C9: 8273.6097 | D9: =IF(C9=C8,D8,D8+1) -> 8 | E9: =MATCH(A9,CorST!$A$2:$A$8126,0) -> 7
A10: это | B10: 5389 | C10: 7160.1868 | D10: =IF(C10=C9,D9,D9+1) -> 9 | E10: =MATCH(A10,CorST!$A$2:$A$8126,0) -> 14
A11: но | B11: 4307 | C11: 5722.569 | D11: =IF(C11=C10,D10,D10+1) -> 10 | E11: =MATCH(A11,CorST!$A$2:$A$8126,0) -> 18
A12: он | B12: 4050 | C12: 5381.1016 | D12: =IF(C12=C11,D11,D11+1) -> 11 | E12: =MATCH(A12,CorST!$A$2:$A$8126,0) -> 20
A13: о | B13: 3780 | C13: 5022.3615 | D13: =IF(C13=C12,D12,D12+1) -> 12 | E13: =MATCH(A13,CorST!$A$2:$A$8126,0) -> 12
A14: для | B14: 3770 | C14: 5009.0748 | D14: =IF(C14=C13,D13,D13+1) -> 13 | E14: =MATCH(A14,CorST!$A$2:$A$8126,0) -> 10
... A8127: ориентировка | B8127: 10 | C8127: 13.286671 | D8127: =IF(C8127=C8126,D8126,D8126+1) -> 4565 | E8127: =MATCH(A8127,CorST!$A$2:$A$8126,0) -> #N/A

Sheet merge
A1: Слово | B1: IPM-CorST | C1: IPM-RLC
A2: сделка | B2: 11520.564
A3: сделать | B3: 10090.806 | C3: 361.39744
A4: сделаны | B4: 4241.1239
A5: сделано | B5: 3791.3953 | C5: 23.916007
A6: сделана | B6: 3647.5848 | C6: 15.944005
A7: сделан | B7: 3295.1208
A8: сделало | B8: 2374.1562 | C8: 27.902008
A9: сделали | B9: 2179.6269 | C9: 73.076688
A10: сделала | B10: 1901.6362 | C10: 51.818015
A11: сделал | B11: 1814.3227 | C11: 61.118685
A12: сделает | B12: 1808.5447 | C12: 25.244674
A13: сдачи | B13: 1576.7787
A14: сдать | B14: 1401.1887 | C14: 17.272672
A15: сдать | B15: 1398.9417 | C15: 17.272672
A16: сдаваться | B16: 1355.606 | C16: 13.286671
A17: священника | B17: 1228.4878
A18: священная | B18: 1162.6817 | C18: 37.202678
A19: святых | B19: 1154.9776
A20: святого | B20: 1134.4332
A21: связь | B21: 944.39801 | C21: 146.15338
A22: связывают | B22: 943.75599
A23: связывается | B23: 872.49279
A24: связывает | B24: 840.07124 | C24: 13.286671
A25: связность | B25: 814.0698
A26: связи | B26: 744.09061 | C26: 186.01339
A27: связей | B27: 742.48558 | C27: 33.216676
A28: связать | B28: 735.10246
A29: связаны | B29: 730.92939 | C29: 119.58003
A30: связанных | B30: 670.25936 | C30: 18.601339
A31: связано | B31: 670.25936 | C31: 93.006694
A32: связанный | B32: 652.60406
A33: связанные | B33: 638.47982 | C33: 50.489348
A34: связанны | B34: 605.09526 | C34: 17.272672
A35: связанную | B35: 601.5642
A36: связанной | B36: 559.51248 | C36: 18.601339
A37: связанное | B37: 553.73438
A38: связанного | B38: 548.27729
A39: связанная | B39: 544.10422
A40: связана | B40: 543.46221 | C40: 63.776019
A41: связан | B41: 528.37495 | C41: 65.104686
A42: свыше | B42: 503.65754 | C42: 31.888009
A43: своя | B43: 501.4105 | C43: 29.230675
A44: свою | B44: 483.43419 | C44: 644.40352
A45: своих | B45: 478.29811 | C45: 499.57881
A46: свойство | B46: 476.69308
A47: свойственны | B47: 452.93868
A48: свойственно | B48: 429.50528
A49: свойствами | B49: 420.19612
A50: свойства | B50: 419.23311 | C50: 18.601339
A51: свойств | B51: 408.96093 | C51: 15.944005
A52: своими | B52: 407.3559 | C52: 216.57273
A53: своим | B53: 401.2568 | C53: 232.51673
A54: свой | B54: 381.99647 | C54: 386.64211
A55: свои | B55: 379.74944 | C55: 488.94948
A56: своеобразным | B56: 369.15626
A57: своеобразный | B57: 365.9462
A58: своеобразной | B58: 364.02017
A59: своеобразное | B59: 359.8471 | C59: 13.286671
A60: своеобразие | B60: 356.63704
A61: своему | B61: 349.57492 | C61: 79.720023
A62: своём | B62: 347.9699 | C62: 67.76202
A63: своем | B63: 345.40185 | C63: 126.22337
A64: своего | B64: 343.47582 | C64: 288.32075
A65: своей | B65: 343.47582 | C65: 713.49421
A66: свое | B66: 340.90778 | C66: 376.01278
A67: своё | B67: 340.90778 | C67: 132.86671
A68: сводится | B68: 337.05571
A69: свободы | B69: 334.80867 | C69: 140.83871
A70: свободу | B70: 332.56164 | C70: 108.9507
A71: свободой | B71: 332.24063
A72: свободных | B72: 323.89449 | C72: 15.944005
A73: свободных | B73: 321.96846 | C73: 15.944005
A74: свободным | B74: 321.64745
A75: свободный | B75: 316.51136 | C75: 17.272672
A76: свободные | B76: 313.94332
A77: свободной | B77: 310.41226 | C77: 41.188679
A78: свободное | B78: 308.48623 | C78: 51.818015
A79: свободного | B79: 306.5602 | C79: 35.87401
A80: свободно | B80: 299.17707 | C80: 67.76202
A81: свободная | B81: 297.57204 | C81: 15.944005
A82: свободе | B82: 296.60903 | C82: 26.573341
A83: свобода | B83: 295.96702 | C83: 151.46804
A84: свобод | B84: 295.004
A85: свидетеля | B85: 291.47294
A86: свидетельствуют | B86: 287.94188
A87: свидетельствует | B87: 287.29987
A88: свидетельство | B88: 286.01585 | C88: 14.615338
A89: свидетельство | B89: 284.73183 | C89: 14.615338
A90: свидетельства | B90: 284.41082 | C90: 18.601339
A91: свидетельств | B91: 282.16378 | C91: 14.615338
A92: свидетельских | B92: 281.84278
A93: свидетели | B93: 267.39753
A94: свидетелей | B94: 267.07653
A95: свидание | B95: 266.75552 | C95: 17.272672
A96: свету | B96: 265.7925
A97: светской | B97: 265.4715 | C97: 37.202678
A98: светлоты | B98: 264.82949
A99: светлота | B99: 258.73038
A100: светлое | B100: 257.44636 | C100: 33.216676
...
